chatting_chatbots/__init__.py
chatting_chatbots/about.py
chatting_chatbots/chatbots.py
chatting_chatbots/generation.py
chatting_chatbots/utils.py
chatting_chatbots-0.0.1.dist-info/LICENSE
chatting_chatbots-0.0.1.dist-info/METADATA
chatting_chatbots-0.0.1.dist-info/WHEEL
chatting_chatbots-0.0.1.dist-info/top_level.txt
chatting_chatbots-0.0.1.dist-info/RECORD
