Metadata-Version: 2.1
Name: chatting-chatbots
Version: 0.0.1
Summary: A library for running experiments of multiple chatbots having conversations with each other.
Home-page: https://github.com/centre-for-humanities-computing/chatbot-conversations
Author: Rokas Maksevičius
License: MIT
Keywords: template
Platform: UNKNOWN
Classifier: Development Status :: 4 - Beta
Classifier: Environment :: Console
Classifier: Intended Audience :: Developers
Classifier: Intended Audience :: Science/Research
Classifier: Topic :: Scientific/Engineering
Classifier: Topic :: Scientific/Engineering :: Artificial Intelligence
Classifier: License :: OSI Approved :: MIT License
Classifier: Operating System :: POSIX :: Linux
Classifier: Operating System :: MacOS :: MacOS X
Classifier: Operating System :: Microsoft :: Windows
Classifier: Programming Language :: Python :: 3
Classifier: Programming Language :: Python :: 3.7
Classifier: Programming Language :: Python :: 3.8
Classifier: Programming Language :: Python :: 3.9
Requires-Python: >=3.7
License-File: LICENSE
Requires-Dist: pandas (==1.3.4)
Requires-Dist: datasets (==1.14.0)
Requires-Dist: numpy (==1.21.2)
Requires-Dist: pytorch-ignite (==0.4.8)
Requires-Dist: scikit-learn (==1.0.2)
Requires-Dist: scipy (==1.7.3)
Requires-Dist: torch (==1.9.1)
Requires-Dist: transformers (==4.12.2)
